ts_backend_check/__init__.py
ts_backend_check/checker.py
ts_backend_check/django_parser.py
ts_backend_check/typescript_parser.py
ts_backend_check/utils.py
ts_backend_check/cli/__init__.py
ts_backend_check/cli/check_blank.py
ts_backend_check/cli/config.py
ts_backend_check/cli/main.py
ts_backend_check/cli/upgrade.py
ts_backend_check/cli/version.py
ts_backend_check/parsers/__init__.py
ts_backend_check/parsers/django_parser.py
ts_backend_check/parsers/typescript_parser.py
ts_backend_check-1.2.2.data/data/requirements.txt
ts_backend_check-1.2.2.dist-info/licenses/LICENSE.txt
ts_backend_check-1.2.2.dist-info/METADATA
ts_backend_check-1.2.2.dist-info/WHEEL
ts_backend_check-1.2.2.dist-info/entry_points.txt
ts_backend_check-1.2.2.dist-info/top_level.txt
ts_backend_check-1.2.2.dist-info/RECORD
