Metadata-Version: 2.4
Name: ts-backend-check
Version: 1.2.2
Summary: Check TypeScript types against their corresponding backend models to assure that all fields have been accounted for.
Home-page: https://github.com/activist-org/ts-backend-check
Author: ts-backend-check developers
Author-email: team@activist.org
License: : OSI Approved :: GNU License
Keywords: backend,typescript,validation,ci,cli
Classifier: Development Status :: 5 - Production/Stable
Classifier: Intended Audience :: Developers
Classifier: License :: OSI Approved :: GNU General Public License v3 (GPLv3)
Classifier: Programming Language :: Python
Classifier: Programming Language :: Python :: 3
Classifier: Programming Language :: Python :: 3.10
Classifier: Programming Language :: Python :: 3.11
Classifier: Programming Language :: Python :: 3.12
Classifier: Programming Language :: Python :: 3.13
Classifier: Programming Language :: Python :: 3.14
Classifier: Operating System :: OS Independent
Requires-Python: >=3.10
License-File: LICENSE.txt
Requires-Dist: certifi>=2025.11.12
Requires-Dist: charset-normalizer>=3.4.4
Requires-Dist: idna>=3.11
Requires-Dist: markdown-it-py>=4.0.0
Requires-Dist: mdurl>=0.1.2
Requires-Dist: pygments>=2.19.2
Requires-Dist: pyyaml>=6.0.3
Requires-Dist: requests>=2.32.5
Requires-Dist: rich>=14.2.0
Requires-Dist: urllib3>=2.6.2
Dynamic: author
Dynamic: author-email
Dynamic: classifier
Dynamic: description
Dynamic: description-content-type
Dynamic: home-page
Dynamic: license-file
Dynamic: requires-dist
Dynamic: requires-python
Dynamic: summary
